pycomplexity/__init__.py
pycomplexity/analyzer.py
pycomplexity/decorators.py
pycomplexity/profiler.py
pycomplexity/tracker.py
pycomplexity/utils.py
pycomplexity-1.0.2.dist-info/licenses/LICENSE
pycomplexity-1.0.2.dist-info/METADATA
pycomplexity-1.0.2.dist-info/WHEEL
pycomplexity-1.0.2.dist-info/top_level.txt
pycomplexity-1.0.2.dist-info/RECORD
