Metadata-Version: 2.4
Name: pycomplexity
Version: 1.0.2
Summary: runtime complexity analyzer for python
Home-page: https://github.com/oracle-dsc/pycomplexity
Author: Oracle
Author-email: Oracle <unknownfrench@proton.me>
License-Expression: MIT
Project-URL: homepage, https://github.com/oracle-dsc/pycomplexity
Classifier: Development Status :: 4 - Beta
Classifier: Intended Audience :: Developers
Classifier: Operating System :: OS Independent
Classifier: Programming Language :: Python :: 3
Requires-Python: >=3.8
License-File: LICENSE
Requires-Dist: numpy>=1.20.0
Dynamic: author
Dynamic: home-page
Dynamic: license-file
Dynamic: requires-python
